ptl_neural_network/cli.py
ptl_neural_network/run.py
ptl_neural_network/train.py
ptl_neural_network-1.0.6.dist-info/licenses/LICENSE
ptl_neural_network-1.0.6.dist-info/METADATA
ptl_neural_network-1.0.6.dist-info/WHEEL
ptl_neural_network-1.0.6.dist-info/entry_points.txt
ptl_neural_network-1.0.6.dist-info/top_level.txt
ptl_neural_network-1.0.6.dist-info/RECORD
