Metadata-Version: 2.4
Name: ptl-neural-network
Version: 1.0.6
Summary: Power Trip Lab's neural network!
License-Expression: LGPL-2.1-only
Project-URL: Source Code, https://github.com/Power-Trip-Labs/neural-network/
Project-URL: Funding, https://power-trip-labs.github.io/funding.html
Requires-Python: >=3.8
License-File: LICENSE
Requires-Dist: numpy
Dynamic: license-file
